{
  "entries": [
    {
      "page": "三体I-01-前言",
      "rev_id": "20260426-191042-edd734",
      "timestamp": "2026-04-26T19:10:42+00:00",
      "author": "baojie",
      "summary": "新增三体全三册原文 Wiki 页面及 PN 引用插件",
      "parent_rev": null,
      "content_hash": "sha256:edd73417e99876c12790bdd7800fc52180540f8d50964c0c6d9a64ea245780f4",
      "size_before": 0,
      "size": 2099
    },
    {
      "page": "三体I-05-三十八年后",
      "rev_id": "20260426-191042-4459dc",
      "timestamp": "2026-04-26T19:10:42+00:00",
      "author": "baojie",
      "summary": "新增三体全三册原文 Wiki 页面及 PN 引用插件",
      "parent_rev": null,
      "content_hash": "sha256:4459dc7dcaa9f1fe9f68c73bd094df3fb05f8ea2ee5472d32323b152f0a0cd66",
      "size_before": 0,
      "size": 25884
    },
    {
      "page": "三体I-06-台球",
      "rev_id": "20260426-191042-9bba1f",
      "timestamp": "2026-04-26T19:10:42+00:00",
      "author": "baojie",
      "summary": "新增三体全三册原文 Wiki 页面及 PN 引用插件",
      "parent_rev": null,
      "content_hash": "sha256:9bba1f565ebb3cae669e0f1cf78723613a3a4a552ff812f4c0f9fb79b8304f05",
      "size_before": 0,
      "size": 8680
    },
    {
      "page": "三体I-07-射手和农场主",
      "rev_id": "20260426-191042-5eb3a8",
      "timestamp": "2026-04-26T19:10:42+00:00",
      "author": "baojie",
      "summary": "新增三体全三册原文 Wiki 页面及 PN 引用插件",
      "parent_rev": null,
      "content_hash": "sha256:5eb3a8b30e2fe9455b91b72076c4f760f8de0bf041a4ee693a66ae74859e2147",
      "size_before": 0,
      "size": 35592
    },
    {
      "page": "三体I-08-周文王·长夜",
      "rev_id": "20260426-191042-1afbab",
      "timestamp": "2026-04-26T19:10:42+00:00",
      "author": "baojie",
      "summary": "新增三体全三册原文 Wiki 页面及 PN 引用插件",
      "parent_rev": null,
      "content_hash": "sha256:1afbabb2cf02f69a8a7b57d1417169ce6c277028fe95c4fd480677667fe20a8e",
      "size_before": 0,
      "size": 27133
    },
    {
      "page": "三体I-11-大史",
      "rev_id": "20260426-191042-da7b01",
      "timestamp": "2026-04-26T19:10:42+00:00",
      "author": "baojie",
      "summary": "新增三体全三册原文 Wiki 页面及 PN 引用插件",
      "parent_rev": null,
      "content_hash": "sha256:da7b01dc8640a4107c62a9bd084dc76b31f784264ead6322b93707dd7a1b7a7c",
      "size_before": 0,
      "size": 12032
    },
    {
      "page": "三体I-17-三体问题",
      "rev_id": "20260426-191042-4fdb50",
      "timestamp": "2026-04-26T19:10:42+00:00",
      "author": "baojie",
      "summary": "新增三体全三册原文 Wiki 页面及 PN 引用插件",
      "parent_rev": null,
      "content_hash": "sha256:4fdb5042f3adb4de76de6b80b995e2da19ad5b0e673b65e8f6d4be1b49117bab",
      "size_before": 0,
      "size": 29508
    },
    {
      "page": "三体III-03-纪年对照表",
      "rev_id": "20260426-191042-3bfcea",
      "timestamp": "2026-04-26T19:10:42+00:00",
      "author": "baojie",
      "summary": "新增三体全三册原文 Wiki 页面及 PN 引用插件",
      "parent_rev": null,
      "content_hash": "sha256:3bfceaaef3e25acb06482fac8fdbbfb1b02d3aab45aba36f733def9d6b37de35",
      "size_before": 0,
      "size": 738
    },
    {
      "page": "三体III-04-第一部·第一章",
      "rev_id": "20260426-191042-f7634e",
      "timestamp": "2026-04-26T19:10:42+00:00",
      "author": "baojie",
      "summary": "新增三体全三册原文 Wiki 页面及 PN 引用插件",
      "parent_rev": null,
      "content_hash": "sha256:f7634e6736e9eb02e41c7236ffa2cb18ffe4ad6362275328f2df9029b4ce3346",
      "size_before": 0,
      "size": 28662
    },
    {
      "page": "三体III-05-第一部·第二章",
      "rev_id": "20260426-191042-b296aa",
      "timestamp": "2026-04-26T19:10:42+00:00",
      "author": "baojie",
      "summary": "新增三体全三册原文 Wiki 页面及 PN 引用插件",
      "parent_rev": null,
      "content_hash": "sha256:b296aa24482f6a81cb41ec7da2655424dcd4c02fefeb9d284585b8fa4cdada17",
      "size_before": 0,
      "size": 10432
    },
    {
      "page": "三体III-32-第三部·第六章",
      "rev_id": "20260426-191042-a63531",
      "timestamp": "2026-04-26T19:10:42+00:00",
      "author": "baojie",
      "summary": "新增三体全三册原文 Wiki 页面及 PN 引用插件",
      "parent_rev": null,
      "content_hash": "sha256:a635318edde9fed8ffd88fae2d0b315230f8015395b729fa95a7ddd72f5b6f87",
      "size_before": 0,
      "size": 26543
    },
    {
      "page": "三体I-02-疯狂年代",
      "rev_id": "20260426-192927-c6cd4d",
      "timestamp": "2026-04-26T19:29:27+00:00",
      "author": "baojie",
      "summary": "Butler R1-R16：新增16个核心词条，页面总数160",
      "parent_rev": "20260426-191042-d13714",
      "content_hash": "sha256:c6cd4d0837fe87452bd62a68f0ba4749ab252fbe8f86e46f15448474a225be67",
      "size_before": 21697,
      "size": 21701
    },
    {
      "page": "三体I-03-寂静的春天",
      "rev_id": "20260426-192927-faf4e0",
      "timestamp": "2026-04-26T19:29:27+00:00",
      "author": "baojie",
      "summary": "Butler R1-R16：新增16个核心词条，页面总数160",
      "parent_rev": "20260426-191042-719515",
      "content_hash": "sha256:faf4e0ef51562020c562db32c524b8fee93fee1553028dbdd30daf8e29060e7a",
      "size_before": 27857,
      "size": 27861
    },
    {
      "page": "三体I-04-红岸之一",
      "rev_id": "20260426-192927-3bedb2",
      "timestamp": "2026-04-26T19:29:27+00:00",
      "author": "baojie",
      "summary": "Butler R1-R16：新增16个核心词条，页面总数160",
      "parent_rev": "20260426-191042-bc6b57",
      "content_hash": "sha256:3bedb29bb841461b00c150716b33acea50a4212b6d03c8e6bb0c4f51962cee81",
      "size_before": 13631,
      "size": 13639
    },
    {
      "page": "三体I-09-叶文洁",
      "rev_id": "20260426-192927-510e22",
      "timestamp": "2026-04-26T19:29:27+00:00",
      "author": "baojie",
      "summary": "Butler R1-R16：新增16个核心词条，页面总数160",
      "parent_rev": "20260426-191042-af6023",
      "content_hash": "sha256:510e22a934cb07598df261930cd2517a1b5126225fa48e584fb7f2935f8ed4a4",
      "size_before": 11179,
      "size": 11183
    },
    {
      "page": "三体I-10-字宙闪烁",
      "rev_id": "20260426-192927-aa5efe",
      "timestamp": "2026-04-26T19:29:27+00:00",
      "author": "baojie",
      "summary": "Butler R1-R16：新增16个核心词条，页面总数160",
      "parent_rev": "20260426-191042-d159a2",
      "content_hash": "sha256:aa5efebd8a70a18a1c1fc5986f2decdb4c56f0ffe33a18f4f1557c339bffe56d",
      "size_before": 18801,
      "size": 18809
    },
    {
      "page": "三体I-12-三体·墨子·烈焰",
      "rev_id": "20260426-192927-4c965c",
      "timestamp": "2026-04-26T19:29:27+00:00",
      "author": "baojie",
      "summary": "Butler R1-R16：新增16个核心词条，页面总数160",
      "parent_rev": "20260426-191042-d3ea79",
      "content_hash": "sha256:4c965c2e9d76999dc77e8e8b85f547a66e31dcc020fbcdc8becdf5eccebeec15",
      "size_before": 20300,
      "size": 20308
    },
    {
      "page": "三体I-13-红岸之二",
      "rev_id": "20260426-192927-8e3d5e",
      "timestamp": "2026-04-26T19:29:27+00:00",
      "author": "baojie",
      "summary": "Butler R1-R16：新增16个核心词条，页面总数160",
      "parent_rev": "20260426-191042-a4ce6f",
      "content_hash": "sha256:8e3d5e6a2092fec8acb1008676f91bc9e6b5057ca4897cd7d2e4d1b4e7c3da52",
      "size_before": 17464,
      "size": 17472
    },
    {
      "page": "三体I-14-红岸之三",
      "rev_id": "20260426-192927-72f066",
      "timestamp": "2026-04-26T19:29:27+00:00",
      "author": "baojie",
      "summary": "Butler R1-R16：新增16个核心词条，页面总数160",
      "parent_rev": "20260426-191042-9ac3cf",
      "content_hash": "sha256:72f066f12081f311edec97db2171cf062bbed40dde2081dbb76f17718faa846b",
      "size_before": 10688,
      "size": 10709
    },
    {
      "page": "三体I-15-红岸之四",
      "rev_id": "20260426-192927-352690",
      "timestamp": "2026-04-26T19:29:27+00:00",
      "author": "baojie",
      "summary": "Butler R1-R16：新增16个核心词条，页面总数160",
      "parent_rev": "20260426-191042-79b03a",
      "content_hash": "sha256:352690c360b642cf98b13aecb7b7c32d8f17698f89134a6ec77fe988879275a5",
      "size_before": 8467,
      "size": 8488
    },
    {
      "page": "三体I-16-三体、哥白尼、宇宙橄榄球、三日凌空",
      "rev_id": "20260426-192927-707c1f",
      "timestamp": "2026-04-26T19:29:27+00:00",
      "author": "baojie",
      "summary": "Butler R1-R16：新增16个核心词条，页面总数160",
      "parent_rev": "20260426-191042-4894fb",
      "content_hash": "sha256:707c1f747ec038261c7843ddadde3731c96662465fae21b5b7b634be12a86d98",
      "size_before": 14200,
      "size": 14208
    },
    {
      "page": "三体I-18-三体、牛顿、冯·诺依曼、秦始皇、三日连珠",
      "rev_id": "20260426-192927-b6a02b",
      "timestamp": "2026-04-26T19:29:27+00:00",
      "author": "baojie",
      "summary": "Butler R1-R16：新增16个核心词条，页面总数160",
      "parent_rev": "20260426-191042-df1a26",
      "content_hash": "sha256:b6a02b72c8b0765a606a7cb2424d58220d1a7e10654c756d7ee08d9eb21d0611",
      "size_before": 29691,
      "size": 29695
    },
    {
      "page": "三体I-19-聚会",
      "rev_id": "20260426-192927-ae71a2",
      "timestamp": "2026-04-26T19:29:27+00:00",
      "author": "baojie",
      "summary": "Butler R1-R16：新增16个核心词条，页面总数160",
      "parent_rev": "20260426-191042-df3124",
      "content_hash": "sha256:ae71a27f6c1f84a2f4e8f0cecec1fb17611a58350961526dca08892c15e2c33f",
      "size_before": 10425,
      "size": 10442
    },
    {
      "page": "三体I-20-三体、爱因斯坦、单摆、大撕裂",
      "rev_id": "20260426-192927-46906a",
      "timestamp": "2026-04-26T19:29:27+00:00",
      "author": "baojie",
      "summary": "Butler R1-R16：新增16个核心词条，页面总数160",
      "parent_rev": "20260426-191042-2d2eb4",
      "content_hash": "sha256:46906a81d06e5df3142eaac2dd04ac2bc8dc11692f3b53ec569ad2319b62514e",
      "size_before": 18675,
      "size": 18679
    },
    {
      "page": "三体I-21-三体、远征",
      "rev_id": "20260426-192927-64ffac",
      "timestamp": "2026-04-26T19:29:27+00:00",
      "author": "baojie",
      "summary": "Butler R1-R16：新增16个核心词条，页面总数160",
      "parent_rev": "20260426-191042-507017",
      "content_hash": "sha256:64ffacfcade87b035b32cac917e0d7d4f9084b61048ee7c684863880ab9b2747",
      "size_before": 4254,
      "size": 4258
    },
    {
      "page": "三体I-22-地球叛军",
      "rev_id": "20260426-192927-e61c3a",
      "timestamp": "2026-04-26T19:29:27+00:00",
      "author": "baojie",
      "summary": "Butler R1-R16：新增16个核心词条，页面总数160",
      "parent_rev": "20260426-191042-1b3ed4",
      "content_hash": "sha256:e61c3a8aa6148acdd1aa946d8acf327fdb86d0c3e266042b9398bb88d38c85ee",
      "size_before": 12922,
      "size": 12930
    },
    {
      "page": "三体I-23-红岸之五",
      "rev_id": "20260426-192927-62702f",
      "timestamp": "2026-04-26T19:29:27+00:00",
      "author": "baojie",
      "summary": "Butler R1-R16：新增16个核心词条，页面总数160",
      "parent_rev": "20260426-191042-468e4e",
      "content_hash": "sha256:62702ff89c70b20dd84ef143d78486c85727fe5f788da1843ede5043704d0d4d",
      "size_before": 19622,
      "size": 19630
    },
    {
      "page": "三体I-24-红岸之六",
      "rev_id": "20260426-192927-2b2b5e",
      "timestamp": "2026-04-26T19:29:27+00:00",
      "author": "baojie",
      "summary": "Butler R1-R16：新增16个核心词条，页面总数160",
      "parent_rev": "20260426-191042-6e9f72",
      "content_hash": "sha256:2b2b5eda86557f680414d5adecab0ac9334a4a286007992238c35b24158b7be4",
      "size_before": 12530,
      "size": 12551
    },
    {
      "page": "三体I-25-叛乱",
      "rev_id": "20260426-192927-892b64",
      "timestamp": "2026-04-26T19:29:27+00:00",
      "author": "baojie",
      "summary": "Butler R1-R16：新增16个核心词条，页面总数160",
      "parent_rev": "20260426-191042-6a9926",
      "content_hash": "sha256:892b643e8620a37977f01cfedfac6d0059944cedafe08c5a2b8a466376e5a278",
      "size_before": 8503,
      "size": 8507
    },
    {
      "page": "三体I-26-雷志成、杨卫宁之死",
      "rev_id": "20260426-192927-d21689",
      "timestamp": "2026-04-26T19:29:27+00:00",
      "author": "baojie",
      "summary": "Butler R1-R16：新增16个核心词条，页面总数160",
      "parent_rev": "20260426-191042-564e00",
      "content_hash": "sha256:d2168928bc66bff11ea54842ddcd021d9ded131c945d047859856f24448da29e",
      "size_before": 8712,
      "size": 8720
    },
    {
      "page": "三体I-27-无人忏悔",
      "rev_id": "20260426-192927-f8b378",
      "timestamp": "2026-04-26T19:29:27+00:00",
      "author": "baojie",
      "summary": "Butler R1-R16：新增16个核心词条，页面总数160",
      "parent_rev": "20260426-191042-6a7d69",
      "content_hash": "sha256:f8b378c5c5c703c21a49acca9aa3450dd746e786dc712fb673d079c716676680",
      "size_before": 23067,
      "size": 23075
    },
    {
      "page": "三体I-28-伊文斯",
      "rev_id": "20260426-192927-9a3e4b",
      "timestamp": "2026-04-26T19:29:27+00:00",
      "author": "baojie",
      "summary": "Butler R1-R16：新增16个核心词条，页面总数160",
      "parent_rev": "20260426-191042-d791e9",
      "content_hash": "sha256:9a3e4ba12f1d66d414f9483176e7964904bfc06ca44c86cbd4844553716718cc",
      "size_before": 16745,
      "size": 16749
    },
    {
      "page": "三体I-29-第二红岸基地",
      "rev_id": "20260426-192927-7cad1b",
      "timestamp": "2026-04-26T19:29:27+00:00",
      "author": "baojie",
      "summary": "Butler R1-R16：新增16个核心词条，页面总数160",
      "parent_rev": "20260426-191042-e1daab",
      "content_hash": "sha256:7cad1b18931b0a33342fc6d4bd309d8aa10cd88669076924e2a71964dcd32fde",
      "size_before": 3468,
      "size": 3480
    },
    {
      "page": "三体I-30-地球三体运动",
      "rev_id": "20260426-192927-2df106",
      "timestamp": "2026-04-26T19:29:27+00:00",
      "author": "baojie",
      "summary": "Butler R1-R16：新增16个核心词条，页面总数160",
      "parent_rev": "20260426-191042-075482",
      "content_hash": "sha256:2df106f87b1a39e13874488c8b82a48ac3a18afdca11975db59ab77ffe0b34ec",
      "size_before": 8423,
      "size": 8431
    },
    {
      "page": "三体I-31-两个质子",
      "rev_id": "20260426-192927-3effaf",
      "timestamp": "2026-04-26T19:29:27+00:00",
      "author": "baojie",
      "summary": "Butler R1-R16：新增16个核心词条，页面总数160",
      "parent_rev": "20260426-191042-90e16a",
      "content_hash": "sha256:3effaf10779ff9a7698ba66d29aee0523fd28f88c03ed87dc6afcd283830eab6",
      "size_before": 12062,
      "size": 12074
    },
    {
      "page": "三体I-32-古筝行动",
      "rev_id": "20260426-192927-6f06aa",
      "timestamp": "2026-04-26T19:29:27+00:00",
      "author": "baojie",
      "summary": "Butler R1-R16：新增16个核心词条，页面总数160",
      "parent_rev": "20260426-191042-a508e9",
      "content_hash": "sha256:6f06aafbcba73195e214a516bcc3b1069b7327b99f715b48bf76ba43113c8420",
      "size_before": 27580,
      "size": 27588
    },
    {
      "page": "三体I-33-监听员",
      "rev_id": "20260426-192927-d099bb",
      "timestamp": "2026-04-26T19:29:27+00:00",
      "author": "baojie",
      "summary": "Butler R1-R16：新增16个核心词条，页面总数160",
      "parent_rev": "20260426-191042-f93e3d",
      "content_hash": "sha256:d099bbfd174c3fb022f7845d24c5810373cf027915eb5c557c684de3cc182023",
      "size_before": 19073,
      "size": 19098
    },
    {
      "page": "三体I-34-智子",
      "rev_id": "20260426-192927-4eacef",
      "timestamp": "2026-04-26T19:29:27+00:00",
      "author": "baojie",
      "summary": "Butler R1-R16：新增16个核心词条，页面总数160",
      "parent_rev": "20260426-191042-9ce07a",
      "content_hash": "sha256:4eaceffc5283126513a70820aff214b302339208524deee4ba9f80dd08fc8751",
      "size_before": 46797,
      "size": 46809
    },
    {
      "page": "三体I-35-虫子",
      "rev_id": "20260426-192927-e8aa28",
      "timestamp": "2026-04-26T19:29:27+00:00",
      "author": "baojie",
      "summary": "Butler R1-R16：新增16个核心词条，页面总数160",
      "parent_rev": "20260426-191042-8711e4",
      "content_hash": "sha256:e8aa2841858d18f2e23edbe7abd3e77764cb18f6a10828961cb726a4ce9cc9d5",
      "size_before": 8815,
      "size": 8836
    },
    {
      "page": "三体I-36-尾声·遗址",
      "rev_id": "20260426-192927-177124",
      "timestamp": "2026-04-26T19:29:27+00:00",
      "author": "baojie",
      "summary": "Butler R1-R16：新增16个核心词条，页面总数160",
      "parent_rev": "20260426-191042-c08a8b",
      "content_hash": "sha256:177124c9bd981fa6733db315544faa077c2973724af4c057b6a63b01d25256ae",
      "size_before": 2704,
      "size": 2716
    },
    {
      "page": "三体I-37-后记",
      "rev_id": "20260426-192927-000a45",
      "timestamp": "2026-04-26T19:29:27+00:00",
      "author": "baojie",
      "summary": "Butler R1-R16：新增16个核心词条，页面总数160",
      "parent_rev": "20260426-191042-f96d41",
      "content_hash": "sha256:000a45f2cab1c67507b4b83524cfa0b399a01b4b6c875c1805a01926ad801eda",
      "size_before": 5464,
      "size": 5487
    },
    {
      "page": "三体II-02-序章",
      "rev_id": "20260426-192927-01d14b",
      "timestamp": "2026-04-26T19:29:27+00:00",
      "author": "baojie",
      "summary": "Butler R1-R16：新增16个核心词条，页面总数160",
      "parent_rev": "20260426-191042-6297c7",
      "content_hash": "sha256:01d14b6984543c83075568256934c74e860653889f6992db23d33f586213d9ad",
      "size_before": 22851,
      "size": 22886
    },
    {
      "page": "三体II-03-上部第1节",
      "rev_id": "20260426-192927-98a82d",
      "timestamp": "2026-04-26T19:29:27+00:00",
      "author": "baojie",
      "summary": "Butler R1-R16：新增16个核心词条，页面总数160",
      "parent_rev": "20260426-191042-2ef626",
      "content_hash": "sha256:98a82dde464ff792245b55221e1dad335d1e8ed5da6843d377f4bb8e498e6401",
      "size_before": 21201,
      "size": 21228
    },
    {
      "page": "三体II-04-上部第2节",
      "rev_id": "20260426-192927-655d5d",
      "timestamp": "2026-04-26T19:29:27+00:00",
      "author": "baojie",
      "summary": "Butler R1-R16：新增16个核心词条，页面总数160",
      "parent_rev": "20260426-191042-f9e9cc",
      "content_hash": "sha256:655d5d4e459fdbe41e5c83580273c0555b66479e276b0d5ae0ca352f3623eb4f",
      "size_before": 20981,
      "size": 21012
    },
    {
      "page": "三体II-05-上部第3节",
      "rev_id": "20260426-192927-225b85",
      "timestamp": "2026-04-26T19:29:27+00:00",
      "author": "baojie",
      "summary": "Butler R1-R16：新增16个核心词条，页面总数160",
      "parent_rev": "20260426-191042-c73d7f",
      "content_hash": "sha256:225b858599a442a27d0a82486091e06ce5db8247925dec1672ff804beef0f3b6",
      "size_before": 20354,
      "size": 20402
    },
    {
      "page": "三体II-06-上部第4节",
      "rev_id": "20260426-192927-cfd6e9",
      "timestamp": "2026-04-26T19:29:27+00:00",
      "author": "baojie",
      "summary": "Butler R1-R16：新增16个核心词条，页面总数160",
      "parent_rev": "20260426-191042-a998dc",
      "content_hash": "sha256:cfd6e92529935cf07cd160c6f3f83b8ee48faa1b8baad9f09ef89f9ca49be508",
      "size_before": 19557,
      "size": 19584
    },
    {
      "page": "三体II-07-上部第5节",
      "rev_id": "20260426-192927-cb4e95",
      "timestamp": "2026-04-26T19:29:27+00:00",
      "author": "baojie",
      "summary": "Butler R1-R16：新增16个核心词条，页面总数160",
      "parent_rev": "20260426-191042-6383dd",
      "content_hash": "sha256:cb4e95191a56ac7bd0278344c62210f71aa519ea95314e085428bb326e070e5c",
      "size_before": 20044,
      "size": 20071
    },
    {
      "page": "三体II-08-上部第6节",
      "rev_id": "20260426-192927-694e16",
      "timestamp": "2026-04-26T19:29:27+00:00",
      "author": "baojie",
      "summary": "Butler R1-R16：新增16个核心词条，页面总数160",
      "parent_rev": "20260426-191042-e07d5c",
      "content_hash": "sha256:694e167f7bed58b12ac9c67bb2bba32cb38f9d79c8f8a76cf37eea7983557d75",
      "size_before": 20642,
      "size": 20669
    },
    {
      "page": "三体II-09-上部第7节",
      "rev_id": "20260426-192927-f59d26",
      "timestamp": "2026-04-26T19:29:27+00:00",
      "author": "baojie",
      "summary": "Butler R1-R16：新增16个核心词条，页面总数160",
      "parent_rev": "20260426-191042-f14882",
      "content_hash": "sha256:f59d26c88e1c999e30f73828e63acd4b079d6847498621f1b4c46bb442c36714",
      "size_before": 21899,
      "size": 21926
    },
    {
      "page": "三体II-10-上部第8节",
      "rev_id": "20260426-192927-79988d",
      "timestamp": "2026-04-26T19:29:27+00:00",
      "author": "baojie",
      "summary": "Butler R1-R16：新增16个核心词条，页面总数160",
      "parent_rev": "20260426-191042-33393b",
      "content_hash": "sha256:79988d65f580f9d3439d2be3f51f4e14c0add0ab52d69f2fbb021817e8e6ac10",
      "size_before": 21658,
      "size": 21706
    },
    {
      "page": "三体II-11-上部第9节",
      "rev_id": "20260426-192927-16b11b",
      "timestamp": "2026-04-26T19:29:27+00:00",
      "author": "baojie",
      "summary": "Butler R1-R16：新增16个核心词条，页面总数160",
      "parent_rev": "20260426-191042-3ceea7",
      "content_hash": "sha256:16b11b37e1fc6050a25692520d3fce39ffee815de4fa8ccd4d1165d6fa0c9aa9",
      "size_before": 21483,
      "size": 21510
    },
    {
      "page": "三体II-12-上部第10节",
      "rev_id": "20260426-192927-5604c8",
      "timestamp": "2026-04-26T19:29:27+00:00",
      "author": "baojie",
      "summary": "Butler R1-R16：新增16个核心词条，页面总数160",
      "parent_rev": "20260426-191042-ff03b6",
      "content_hash": "sha256:5604c8c55e6ca8a7149f2351a2a39f0c831e0d3df886ab5355a9f5741878ece4",
      "size_before": 20883,
      "size": 20931
    },
    {
      "page": "三体II-13-上部第11节",
      "rev_id": "20260426-192927-d45d13",
      "timestamp": "2026-04-26T19:29:27+00:00",
      "author": "baojie",
      "summary": "Butler R1-R16：新增16个核心词条，页面总数160",
      "parent_rev": "20260426-191042-e6bb56",
      "content_hash": "sha256:d45d13c17334d43a18fba50603b9167ea636724bae31f1ce31a0eb83f07157eb",
      "size_before": 19736,
      "size": 19780
    },
    {
      "page": "三体II-14-上部第12节",
      "rev_id": "20260426-192927-4e686c",
      "timestamp": "2026-04-26T19:29:27+00:00",
      "author": "baojie",
      "summary": "Butler R1-R16：新增16个核心词条，页面总数160",
      "parent_rev": "20260426-191042-47f058",
      "content_hash": "sha256:4e686cbeb07612faf11ae65696a3db85d49e90e87a4df21da24b99de89156187",
      "size_before": 22478,
      "size": 22526
    },
    {
      "page": "三体II-15-上部第13节",
      "rev_id": "20260426-192927-a588e9",
      "timestamp": "2026-04-26T19:29:27+00:00",
      "author": "baojie",
      "summary": "Butler R1-R16：新增16个核心词条，页面总数160",
      "parent_rev": "20260426-191042-b07112",
      "content_hash": "sha256:a588e90455f83796b762ebfb4f8d2e38543d0aa84fd59e966ece81385ac033c0",
      "size_before": 21707,
      "size": 21742
    },
    {
      "page": "三体II-16-上部第14节",
      "rev_id": "20260426-192927-5c3ee9",
      "timestamp": "2026-04-26T19:29:27+00:00",
      "author": "baojie",
      "summary": "Butler R1-R16：新增16个核心词条，页面总数160",
      "parent_rev": "20260426-191042-2f8405",
      "content_hash": "sha256:5c3ee96a7868739d79e1edea9799426e1b609e3bbeebe539b7e7faf2e74c9410",
      "size_before": 21940,
      "size": 21971
    },
    {
      "page": "三体II-17-上部第15节",
      "rev_id": "20260426-192927-78aeac",
      "timestamp": "2026-04-26T19:29:27+00:00",
      "author": "baojie",
      "summary": "Butler R1-R16：新增16个核心词条，页面总数160",
      "parent_rev": "20260426-191042-c11151",
      "content_hash": "sha256:78aeace8bf7642f9e15c9b6dda608515baaf88918879c7b3a4ecbc7f885318d6",
      "size_before": 19610,
      "size": 19645
    },
    {
      "page": "三体II-18-上部第16节",
      "rev_id": "20260426-192927-bb6f15",
      "timestamp": "2026-04-26T19:29:27+00:00",
      "author": "baojie",
      "summary": "Butler R1-R16：新增16个核心词条，页面总数160",
      "parent_rev": "20260426-191042-743050",
      "content_hash": "sha256:bb6f150316c0c027307c1c3ef14731bb86fb4ad94e1b23cfcbceab4e29932a48",
      "size_before": 18992,
      "size": 19040
    },
    {
      "page": "三体II-19-中部第1节",
      "rev_id": "20260426-192927-771374",
      "timestamp": "2026-04-26T19:29:27+00:00",
      "author": "baojie",
      "summary": "Butler R1-R16：新增16个核心词条，页面总数160",
      "parent_rev": "20260426-191042-f02a10",
      "content_hash": "sha256:771374010d1a2f5ecc58a772f02806050ad3982f13dcb4de83336330407a5235",
      "size_before": 21266,
      "size": 21293
    },
    {
      "page": "三体II-20-中部第2节",
      "rev_id": "20260426-192927-e8d660",
      "timestamp": "2026-04-26T19:29:27+00:00",
      "author": "baojie",
      "summary": "Butler R1-R16：新增16个核心词条，页面总数160",
      "parent_rev": "20260426-191042-067701",
      "content_hash": "sha256:e8d660af3f3466b75bdc386b33cdd963c7ca3dbb76f7cc2d11d9c6a7c51f67eb",
      "size_before": 20613,
      "size": 20644
    },
    {
      "page": "三体II-21-中部第3节",
      "rev_id": "20260426-192927-cb2d0a",
      "timestamp": "2026-04-26T19:29:27+00:00",
      "author": "baojie",
      "summary": "Butler R1-R16：新增16个核心词条，页面总数160",
      "parent_rev": "20260426-191042-c2fcdb",
      "content_hash": "sha256:cb2d0a69a78d809641c51c03b594ca2979b45ffb3f212f56d41fc8693a99848e",
      "size_before": 21119,
      "size": 21154
    },
    {
      "page": "三体II-22-中部第4节",
      "rev_id": "20260426-192927-7f4586",
      "timestamp": "2026-04-26T19:29:27+00:00",
      "author": "baojie",
      "summary": "Butler R1-R16：新增16个核心词条，页面总数160",
      "parent_rev": "20260426-191042-c22ae4",
      "content_hash": "sha256:7f4586b342aacb1c511d3977a4ac5d1001c10189f61084ec8facea9b768b2f4b",
      "size_before": 22209,
      "size": 22248
    },
    {
      "page": "三体II-23-中部第5节",
      "rev_id": "20260426-192927-4b63e0",
      "timestamp": "2026-04-26T19:29:27+00:00",
      "author": "baojie",
      "summary": "Butler R1-R16：新增16个核心词条，页面总数160",
      "parent_rev": "20260426-191042-341a2c",
      "content_hash": "sha256:4b63e00df67afb20b8b2f0a579a9012770f2460d9356deb631fc86dc2fb1cea9",
      "size_before": 21595,
      "size": 21643
    },
    {
      "page": "三体II-24-中部第6节",
      "rev_id": "20260426-192927-f6fa96",
      "timestamp": "2026-04-26T19:29:27+00:00",
      "author": "baojie",
      "summary": "Butler R1-R16：新增16个核心词条，页面总数160",
      "parent_rev": "20260426-191042-9b572c",
      "content_hash": "sha256:f6fa9625408352ca9de25f22a06318de7d362e1ffaf2244c70b0cc6b13051fed",
      "size_before": 21818,
      "size": 21862
    },
    {
      "page": "三体II-25-中部第7节",
      "rev_id": "20260426-192927-558269",
      "timestamp": "2026-04-26T19:29:27+00:00",
      "author": "baojie",
      "summary": "Butler R1-R16：新增16个核心词条，页面总数160",
      "parent_rev": "20260426-191042-878645",
      "content_hash": "sha256:55826974d04b2458ff83b2de5521878c0a84d0a11973f265e7d772a59bc85f74",
      "size_before": 16192,
      "size": 16223
    },
    {
      "page": "三体II-26-中部第8节",
      "rev_id": "20260426-192927-7126c0",
      "timestamp": "2026-04-26T19:29:27+00:00",
      "author": "baojie",
      "summary": "Butler R1-R16：新增16个核心词条，页面总数160",
      "parent_rev": "20260426-191042-062be8",
      "content_hash": "sha256:7126c0f488e394ea4656876ab34f549ed718da46fe92b93671119d20099fc953",
      "size_before": 20202,
      "size": 20233
    },
    {
      "page": "三体II-27-中部第9节",
      "rev_id": "20260426-192927-87e23a",
      "timestamp": "2026-04-26T19:29:27+00:00",
      "author": "baojie",
      "summary": "Butler R1-R16：新增16个核心词条，页面总数160",
      "parent_rev": "20260426-191042-177348",
      "content_hash": "sha256:87e23a47625eca323b0833fa7a4fc02a3ccadcdf2409afb7d49247ec62f3aafe",
      "size_before": 20059,
      "size": 20086
    },
    {
      "page": "三体II-28-中部第10节",
      "rev_id": "20260426-192927-335777",
      "timestamp": "2026-04-26T19:29:27+00:00",
      "author": "baojie",
      "summary": "Butler R1-R16：新增16个核心词条，页面总数160",
      "parent_rev": "20260426-191042-d6f2ea",
      "content_hash": "sha256:3357774528b63ea3303441f1a6b45645d8f4910920cd69bad1a8a99274c9866a",
      "size_before": 19858,
      "size": 19889
    },
    {
      "page": "三体II-29-中部第11节",
      "rev_id": "20260426-192927-24d926",
      "timestamp": "2026-04-26T19:29:27+00:00",
      "author": "baojie",
      "summary": "Butler R1-R16：新增16个核心词条，页面总数160",
      "parent_rev": "20260426-191042-3fb877",
      "content_hash": "sha256:24d926abaa6aedfe1a019723efecd7ddb55de211072b843918160d5022f84986",
      "size_before": 16321,
      "size": 16348
    },
    {
      "page": "三体II-30-中部第12节",
      "rev_id": "20260426-192927-191cfc",
      "timestamp": "2026-04-26T19:29:27+00:00",
      "author": "baojie",
      "summary": "Butler R1-R16：新增16个核心词条，页面总数160",
      "parent_rev": "20260426-191042-b721ea",
      "content_hash": "sha256:191cfcf50826b588dff0a8abe03766418e10f73edc7b6eb1229c8c8e089bac85",
      "size_before": 17606,
      "size": 17654
    },
    {
      "page": "三体II-31-下部第1节",
      "rev_id": "20260426-192927-0689ab",
      "timestamp": "2026-04-26T19:29:27+00:00",
      "author": "baojie",
      "summary": "Butler R1-R16：新增16个核心词条，页面总数160",
      "parent_rev": "20260426-191042-897fb9",
      "content_hash": "sha256:0689abaf4220359817556e26de7d2a84ee459740b19c766d4e94e4e41a52fe1f",
      "size_before": 19826,
      "size": 19870
    },
    {
      "page": "三体II-32-下部第2节",
      "rev_id": "20260426-192927-e52aa2",
      "timestamp": "2026-04-26T19:29:27+00:00",
      "author": "baojie",
      "summary": "Butler R1-R16：新增16个核心词条，页面总数160",
      "parent_rev": "20260426-191042-ff6d16",
      "content_hash": "sha256:e52aa2f660fce07819128ba69a76d202d6074f5e5cda81bb179be0d1f8cce7d0",
      "size_before": 20771,
      "size": 20802
    },
    {
      "page": "三体II-33-下部第3节",
      "rev_id": "20260426-192927-0807cf",
      "timestamp": "2026-04-26T19:29:27+00:00",
      "author": "baojie",
      "summary": "Butler R1-R16：新增16个核心词条，页面总数160",
      "parent_rev": "20260426-191042-17797e",
      "content_hash": "sha256:0807cf71a83f3961e8b912a69d325ce7bf66586c0ff1b0fb8260521860aa31c6",
      "size_before": 22045,
      "size": 22076
    },
    {
      "page": "三体II-34-下部第4节",
      "rev_id": "20260426-192927-887aac",
      "timestamp": "2026-04-26T19:29:27+00:00",
      "author": "baojie",
      "summary": "Butler R1-R16：新增16个核心词条，页面总数160",
      "parent_rev": "20260426-191042-b2a8ba",
      "content_hash": "sha256:887aacd6a4349ff7facc58585415f693bee9b855058c0c4856e99dae8a81b472",
      "size_before": 20824,
      "size": 20855
    },
    {
      "page": "三体II-35-下部第5节",
      "rev_id": "20260426-192927-105dfd",
      "timestamp": "2026-04-26T19:29:27+00:00",
      "author": "baojie",
      "summary": "Butler R1-R16：新增16个核心词条，页面总数160",
      "parent_rev": "20260426-191042-76b4e3",
      "content_hash": "sha256:105dfdcc776b7c941b0179fa409482f7b60f993e5247b9c1ddf6819321d85000",
      "size_before": 20057,
      "size": 20084
    },
    {
      "page": "三体II-36-下部第6节",
      "rev_id": "20260426-192927-d5dc4e",
      "timestamp": "2026-04-26T19:29:27+00:00",
      "author": "baojie",
      "summary": "Butler R1-R16：新增16个核心词条，页面总数160",
      "parent_rev": "20260426-191042-191d8f",
      "content_hash": "sha256:d5dc4ea2fe5205ce35132c284fbb3943dab6c584741dd97fdb98ddfd2d1a37ba",
      "size_before": 20918,
      "size": 20962
    },
    {
      "page": "三体II-37-下部第7节",
      "rev_id": "20260426-192927-b6c37d",
      "timestamp": "2026-04-26T19:29:27+00:00",
      "author": "baojie",
      "summary": "Butler R1-R16：新增16个核心词条，页面总数160",
      "parent_rev": "20260426-191042-33fa66",
      "content_hash": "sha256:b6c37dc2bdc2aff054508b4f652899cad883965b61521708143d424833a4d8a3",
      "size_before": 21375,
      "size": 21402
    },
    {
      "page": "三体II-38-下部第8节",
      "rev_id": "20260426-192927-eded1d",
      "timestamp": "2026-04-26T19:29:27+00:00",
      "author": "baojie",
      "summary": "Butler R1-R16：新增16个核心词条，页面总数160",
      "parent_rev": "20260426-191042-b9d2ae",
      "content_hash": "sha256:eded1de22393b2d9e5c96f4231a46d61205e73a0f1f17797c5a87d8ae21129b0",
      "size_before": 20546,
      "size": 20569
    },
    {
      "page": "三体II-39-下部第9节",
      "rev_id": "20260426-192927-d6ed20",
      "timestamp": "2026-04-26T19:29:27+00:00",
      "author": "baojie",
      "summary": "Butler R1-R16：新增16个核心词条，页面总数160",
      "parent_rev": "20260426-191042-40c655",
      "content_hash": "sha256:d6ed201bdc67f179f4ba13f3e617f927c79d32833de588afabd237ec30cee354",
      "size_before": 19665,
      "size": 19713
    },
    {
      "page": "三体II-40-下部第10节",
      "rev_id": "20260426-192927-a53531",
      "timestamp": "2026-04-26T19:29:27+00:00",
      "author": "baojie",
      "summary": "Butler R1-R16：新增16个核心词条，页面总数160",
      "parent_rev": "20260426-191042-8cb648",
      "content_hash": "sha256:a53531177b457a8336607b9e7c311358d202c8121f3b937c31237c95f77ae98e",
      "size_before": 19388,
      "size": 19411
    },
    {
      "page": "三体II-41-下部第11节",
      "rev_id": "20260426-192927-9980ae",
      "timestamp": "2026-04-26T19:29:27+00:00",
      "author": "baojie",
      "summary": "Butler R1-R16：新增16个核心词条，页面总数160",
      "parent_rev": "20260426-191042-fe2a6f",
      "content_hash": "sha256:9980ae47e55e064d568e33af1c8d1cd4cd538ec099bb2d874cfb239fac6a3074",
      "size_before": 19539,
      "size": 19570
    },
    {
      "page": "三体II-42-下部第12节",
      "rev_id": "20260426-192927-d2b862",
      "timestamp": "2026-04-26T19:29:27+00:00",
      "author": "baojie",
      "summary": "Butler R1-R16：新增16个核心词条，页面总数160",
      "parent_rev": "20260426-191042-d0699d",
      "content_hash": "sha256:d2b8623a63a6bc8cb83e731488c8dd475dcbb7fe11927e5912cdfb0465c2f303",
      "size_before": 21379,
      "size": 21402
    },
    {
      "page": "三体II-43-下部第13节",
      "rev_id": "20260426-192927-4545b7",
      "timestamp": "2026-04-26T19:29:27+00:00",
      "author": "baojie",
      "summary": "Butler R1-R16：新增16个核心词条，页面总数160",
      "parent_rev": "20260426-191042-fbf55a",
      "content_hash": "sha256:4545b78809e3adec760d1416fdcd51af7aafe0476ad06d9903c6dc3473b2c78e",
      "size_before": 20933,
      "size": 20960
    },
    {
      "page": "三体II-44-下部第14节",
      "rev_id": "20260426-192927-e3bbcd",
      "timestamp": "2026-04-26T19:29:27+00:00",
      "author": "baojie",
      "summary": "Butler R1-R16：新增16个核心词条，页面总数160",
      "parent_rev": "20260426-191042-12a0e7",
      "content_hash": "sha256:e3bbcd783e81d43fb54913b42a07669a81cea1bfeab44ec514012dd5a12f1679",
      "size_before": 20571,
      "size": 20598
    },
    {
      "page": "三体II-45-下部第15节",
      "rev_id": "20260426-192927-489f5e",
      "timestamp": "2026-04-26T19:29:27+00:00",
      "author": "baojie",
      "summary": "Butler R1-R16：新增16个核心词条，页面总数160",
      "parent_rev": "20260426-191042-e96c5c",
      "content_hash": "sha256:489f5e7a25ffe3978ac293c4786fd88e8a26d651fc294aab0c4ec2ae13b71459",
      "size_before": 22035,
      "size": 22058
    },
    {
      "page": "三体II-46-下部第16节",
      "rev_id": "20260426-192927-ae25c0",
      "timestamp": "2026-04-26T19:29:27+00:00",
      "author": "baojie",
      "summary": "Butler R1-R16：新增16个核心词条，页面总数160",
      "parent_rev": "20260426-191042-40e2c2",
      "content_hash": "sha256:ae25c0f44f8ff59f64f8ea9db13dae5911f3b104dba58a3479f48f4c809f7d8e",
      "size_before": 20633,
      "size": 20677
    },
    {
      "page": "三体II-47-下部第17节",
      "rev_id": "20260426-192927-cb4599",
      "timestamp": "2026-04-26T19:29:27+00:00",
      "author": "baojie",
      "summary": "Butler R1-R16：新增16个核心词条，页面总数160",
      "parent_rev": "20260426-191042-4ab11e",
      "content_hash": "sha256:cb4599ab358ad91aaa49c2a547e2e9616557aff4415a734b564c28d50670a310",
      "size_before": 21832,
      "size": 21859
    },
    {
      "page": "三体II-48-下部第18节",
      "rev_id": "20260426-192927-503afd",
      "timestamp": "2026-04-26T19:29:27+00:00",
      "author": "baojie",
      "summary": "Butler R1-R16：新增16个核心词条，页面总数160",
      "parent_rev": "20260426-191042-83564c",
      "content_hash": "sha256:503afd7ef505eab3977eb5ca89bb77cc1e080f363aedb969ab95c29ee3e3506c",
      "size_before": 23127,
      "size": 23154
    },
    {
      "page": "三体II-49-下部第19节",
      "rev_id": "20260426-192927-8570d1",
      "timestamp": "2026-04-26T19:29:27+00:00",
      "author": "baojie",
      "summary": "Butler R1-R16：新增16个核心词条，页面总数160",
      "parent_rev": "20260426-191042-554354",
      "content_hash": "sha256:8570d17507fcae9ce7159ef5217848c80398ed2cbd407bf5e6e50e961f405c7d",
      "size_before": 17882,
      "size": 17909
    },
    {
      "page": "三体II-50-下部第20节",
      "rev_id": "20260426-192927-be3b32",
      "timestamp": "2026-04-26T19:29:27+00:00",
      "author": "baojie",
      "summary": "Butler R1-R16：新增16个核心词条，页面总数160",
      "parent_rev": "20260426-191042-683ce0",
      "content_hash": "sha256:be3b32173f18aa62f16632f6e4e2b1d616ef0b619ce0247b3dba02a3b6f37a54",
      "size_before": 17405,
      "size": 17444
    },
    {
      "page": "三体II-51-下部第21节",
      "rev_id": "20260426-192927-e22314",
      "timestamp": "2026-04-26T19:29:27+00:00",
      "author": "baojie",
      "summary": "Butler R1-R16：新增16个核心词条，页面总数160",
      "parent_rev": "20260426-191042-208108",
      "content_hash": "sha256:e22314afaac92942ac4cde7912423ad5c2170b030d8abde1ee3fbd92187c9a96",
      "size_before": 14902,
      "size": 14954
    },
    {
      "page": "三体III-01-前言",
      "rev_id": "20260426-192927-8c6f1f",
      "timestamp": "2026-04-26T19:29:27+00:00",
      "author": "baojie",
      "summary": "Butler R1-R16：新增16个核心词条，页面总数160",
      "parent_rev": "20260426-191042-6b5147",
      "content_hash": "sha256:8c6f1f0c7d208ac29851b3b17c77ed66050f2ba61a69bbeb01866b6224bec8b3",
      "size_before": 7206,
      "size": 7233
    },
    {
      "page": "三体III-02-序",
      "rev_id": "20260426-192927-495110",
      "timestamp": "2026-04-26T19:29:27+00:00",
      "author": "baojie",
      "summary": "Butler R1-R16：新增16个核心词条，页面总数160",
      "parent_rev": "20260426-191042-c21fd6",
      "content_hash": "sha256:495110c121e0a0196cd63f7827a7408e795316b935e178dff611e93e37f98ab2",
      "size_before": 5769,
      "size": 5809
    },
    {
      "page": "三体III-06-第一部·第三章",
      "rev_id": "20260426-192927-a75b14",
      "timestamp": "2026-04-26T19:29:27+00:00",
      "author": "baojie",
      "summary": "Butler R1-R16：新增16个核心词条，页面总数160",
      "parent_rev": "20260426-191042-77d3a3",
      "content_hash": "sha256:a75b145bc887e69d672f4b0b7df0890024c4621a0fde15c2dc4f1ce12037da1c",
      "size_before": 18032,
      "size": 18036
    },
    {
      "page": "三体III-07-第一部·第四章",
      "rev_id": "20260426-192927-3b0500",
      "timestamp": "2026-04-26T19:29:27+00:00",
      "author": "baojie",
      "summary": "Butler R1-R16：新增16个核心词条，页面总数160",
      "parent_rev": "20260426-191042-4b5f61",
      "content_hash": "sha256:3b0500a82bf0e3101fc8e1540d250d7d97c8ab0bd12a91916fe5ef821a9b7b6c",
      "size_before": 31347,
      "size": 31351
    },
    {
      "page": "三体III-08-第一部·第五章",
      "rev_id": "20260426-192927-5890b0",
      "timestamp": "2026-04-26T19:29:27+00:00",
      "author": "baojie",
      "summary": "Butler R1-R16：新增16个核心词条，页面总数160",
      "parent_rev": "20260426-191042-0e59fc",
      "content_hash": "sha256:5890b0b2f18de1f7df6dea5c86f0fa89c8260ae53510f0f956c571fabf7a5e07",
      "size_before": 27017,
      "size": 27042
    },
    {
      "page": "三体III-09-第一部·第六章",
      "rev_id": "20260426-192927-673b48",
      "timestamp": "2026-04-26T19:29:27+00:00",
      "author": "baojie",
      "summary": "Butler R1-R16：新增16个核心词条，页面总数160",
      "parent_rev": "20260426-191042-9c079d",
      "content_hash": "sha256:673b4815b102c60f853df94278d2a1ebbb97f3fc913ab49162dd10e7b6c0af62",
      "size_before": 14230,
      "size": 14255
    },
    {
      "page": "三体III-10-第一部·第七章",
      "rev_id": "20260426-192927-4b01f7",
      "timestamp": "2026-04-26T19:29:27+00:00",
      "author": "baojie",
      "summary": "Butler R1-R16：新增16个核心词条，页面总数160",
      "parent_rev": "20260426-191042-e15c1a",
      "content_hash": "sha256:4b01f7b5dcd2c09a5d41133129765bc20bb3176aae6eb6fb034845e424209c4e",
      "size_before": 18173,
      "size": 18194
    },
    {
      "page": "三体III-11-第一部·第八章",
      "rev_id": "20260426-192927-5c3176",
      "timestamp": "2026-04-26T19:29:27+00:00",
      "author": "baojie",
      "summary": "Butler R1-R16：新增16个核心词条，页面总数160",
      "parent_rev": "20260426-191042-fc3415",
      "content_hash": "sha256:5c317607d7829f4d6772a8ec9c4917ca16849a60885aba8c2955dd831cacebde",
      "size_before": 22228,
      "size": 22236
    },
    {
      "page": "三体III-12-第二部·第一章",
      "rev_id": "20260426-192927-a53409",
      "timestamp": "2026-04-26T19:29:27+00:00",
      "author": "baojie",
      "summary": "Butler R1-R16：新增16个核心词条，页面总数160",
      "parent_rev": "20260426-191042-0ef57a",
      "content_hash": "sha256:a53409ab3cdfb63cee459bd28082841c1d2509b1f24549dba6fc03a1be012eb1",
      "size_before": 10520,
      "size": 10551
    },
    {
      "page": "三体III-13-第二部·第二章",
      "rev_id": "20260426-192927-21ba29",
      "timestamp": "2026-04-26T19:29:27+00:00",
      "author": "baojie",
      "summary": "Butler R1-R16：新增16个核心词条，页面总数160",
      "parent_rev": "20260426-191042-d08d3f",
      "content_hash": "sha256:21ba299e7a84b52c8126f91c667f26395401ebbbc3511115a16364597060dd38",
      "size_before": 16442,
      "size": 16469
    },
    {
      "page": "三体III-14-第二部·第三章",
      "rev_id": "20260426-192927-d7020d",
      "timestamp": "2026-04-26T19:29:27+00:00",
      "author": "baojie",
      "summary": "Butler R1-R16：新增16个核心词条，页面总数160",
      "parent_rev": "20260426-191042-fd82c9",
      "content_hash": "sha256:d7020d16c8f5d7c263d54cde4907bddabb44e7025d02039ec9016a304135e6fe",
      "size_before": 17077,
      "size": 17125
    },
    {
      "page": "三体III-15-第二部·第四章",
      "rev_id": "20260426-192927-146385",
      "timestamp": "2026-04-26T19:29:27+00:00",
      "author": "baojie",
      "summary": "Butler R1-R16：新增16个核心词条，页面总数160",
      "parent_rev": "20260426-191042-d1cdf2",
      "content_hash": "sha256:14638574485e1dba12c4208994fe83fe16f833d4a32b16cd79a5c6c420e73c6e",
      "size_before": 13555,
      "size": 13607
    },
    {
      "page": "三体III-16-第二部·第五章",
      "rev_id": "20260426-192927-021a92",
      "timestamp": "2026-04-26T19:29:27+00:00",
      "author": "baojie",
      "summary": "Butler R1-R16：新增16个核心词条，页面总数160",
      "parent_rev": "20260426-191042-367520",
      "content_hash": "sha256:021a92a14f18a0901c7ca919980566e6527099db7a0ef23c9392a3073ca2b3b3",
      "size_before": 22561,
      "size": 22617
    },
    {
      "page": "三体III-17-第二部·第六章",
      "rev_id": "20260426-192927-96d58d",
      "timestamp": "2026-04-26T19:29:27+00:00",
      "author": "baojie",
      "summary": "Butler R1-R16：新增16个核心词条，页面总数160",
      "parent_rev": "20260426-191042-f17f2a",
      "content_hash": "sha256:96d58db41b7543550a88a5a11d05ec062b1fa4beadb4a54afb44d54c8674237b",
      "size_before": 4330,
      "size": 4334
    },
    {
      "page": "三体III-18-第二部·第七章",
      "rev_id": "20260426-192927-c381d7",
      "timestamp": "2026-04-26T19:29:27+00:00",
      "author": "baojie",
      "summary": "Butler R1-R16：新增16个核心词条，页面总数160",
      "parent_rev": "20260426-191042-a3236c",
      "content_hash": "sha256:c381d7cf22a81e57acc3d542944fe25c5394d671c1d3b76f82c06a44e65a851c",
      "size_before": 30021,
      "size": 30048
    },
    {
      "page": "三体III-19-第二部·第八章",
      "rev_id": "20260426-192927-697eeb",
      "timestamp": "2026-04-26T19:29:27+00:00",
      "author": "baojie",
      "summary": "Butler R1-R16：新增16个核心词条，页面总数160",
      "parent_rev": "20260426-191042-3f83fc",
      "content_hash": "sha256:697eeb146672258a5313eb2c4ff828a3e3eace12d228166d445ffd8d9e38ef6d",
      "size_before": 18909,
      "size": 18948
    },
    {
      "page": "三体III-20-第二部·第九章",
      "rev_id": "20260426-192927-6fcba5",
      "timestamp": "2026-04-26T19:29:27+00:00",
      "author": "baojie",
      "summary": "Butler R1-R16：新增16个核心词条，页面总数160",
      "parent_rev": "20260426-191042-180b9b",
      "content_hash": "sha256:6fcba577bfd9d364c6adc4d4b06e9b1811c785338c31099d62b0645a477853dc",
      "size_before": 11078,
      "size": 11109
    },
    {
      "page": "三体III-21-第二部·第十章",
      "rev_id": "20260426-192927-f1e4ac",
      "timestamp": "2026-04-26T19:29:27+00:00",
      "author": "baojie",
      "summary": "Butler R1-R16：新增16个核心词条，页面总数160",
      "parent_rev": "20260426-191042-316bb0",
      "content_hash": "sha256:f1e4ac6fcdad44f2b7b67a8cd09dcc88cd5a1e74fe392aa975d87bfadabad939",
      "size_before": 13827,
      "size": 13862
    },
    {
      "page": "三体III-22-第二部·第十一章",
      "rev_id": "20260426-192927-e2b8d5",
      "timestamp": "2026-04-26T19:29:27+00:00",
      "author": "baojie",
      "summary": "Butler R1-R16：新增16个核心词条，页面总数160",
      "parent_rev": "20260426-191042-35645b",
      "content_hash": "sha256:e2b8d5e8c9cca88dec7b91005279a6c3ea60e210dfb5627966904138b3dee0e6",
      "size_before": 9729,
      "size": 9773
    },
    {
      "page": "三体III-23-第二部·第十二章",
      "rev_id": "20260426-192927-a7c39a",
      "timestamp": "2026-04-26T19:29:27+00:00",
      "author": "baojie",
      "summary": "Butler R1-R16：新增16个核心词条，页面总数160",
      "parent_rev": "20260426-191042-f7203e",
      "content_hash": "sha256:a7c39a0096c2536e839d2a1c2e75f8e4033fd75f209b8382f2b25ce186b36b63",
      "size_before": 53881,
      "size": 53906
    },
    {
      "page": "三体III-24-第二部·第十三章",
      "rev_id": "20260426-192927-0139c5",
      "timestamp": "2026-04-26T19:29:27+00:00",
      "author": "baojie",
      "summary": "Butler R1-R16：新增16个核心词条，页面总数160",
      "parent_rev": "20260426-191042-0a5b16",
      "content_hash": "sha256:0139c511044fc07db5d0345a587ae3ec1fae033401a3a89ddcd5494bb002e9bd",
      "size_before": 36865,
      "size": 36900
    },
    {
      "page": "三体III-25-第二部·第十四章",
      "rev_id": "20260426-192927-b1bfab",
      "timestamp": "2026-04-26T19:29:27+00:00",
      "author": "baojie",
      "summary": "Butler R1-R16：新增16个核心词条，页面总数160",
      "parent_rev": "20260426-191042-483eb1",
      "content_hash": "sha256:b1bfab359f7f24173f6ed9e008849d7742cc27a770202a415870b4444567608d",
      "size_before": 4163,
      "size": 4188
    },
    {
      "page": "三体III-26-第二部·第十五章",
      "rev_id": "20260426-192927-6feae0",
      "timestamp": "2026-04-26T19:29:27+00:00",
      "author": "baojie",
      "summary": "Butler R1-R16：新增16个核心词条，页面总数160",
      "parent_rev": "20260426-191042-1c8a5e",
      "content_hash": "sha256:6feae064740fd8f4ae7b3e51c39a362ef3f406400bde31823a0d6aaa0d72011b",
      "size_before": 44042,
      "size": 44065
    },
    {
      "page": "三体III-27-第三部·第一章",
      "rev_id": "20260426-192927-ffd77e",
      "timestamp": "2026-04-26T19:29:27+00:00",
      "author": "baojie",
      "summary": "Butler R1-R16：新增16个核心词条，页面总数160",
      "parent_rev": "20260426-191042-1c79bf",
      "content_hash": "sha256:ffd77e14861e83ab01c0473341aecccf0e42e80106915f4de61b20cdb8fbe19c",
      "size_before": 12431,
      "size": 12466
    },
    {
      "page": "三体III-28-第三部·第二章",
      "rev_id": "20260426-192927-76d0e1",
      "timestamp": "2026-04-26T19:29:27+00:00",
      "author": "baojie",
      "summary": "Butler R1-R16：新增16个核心词条，页面总数160",
      "parent_rev": "20260426-191042-c45fa2",
      "content_hash": "sha256:76d0e146458ef7efb99dc761c86a4487965ff829d96462d8e0fb12475fdf1ab3",
      "size_before": 16452,
      "size": 16504
    },
    {
      "page": "三体III-29-第三部·第三章",
      "rev_id": "20260426-192927-892fe0",
      "timestamp": "2026-04-26T19:29:27+00:00",
      "author": "baojie",
      "summary": "Butler R1-R16：新增16个核心词条，页面总数160",
      "parent_rev": "20260426-191042-12aa3d",
      "content_hash": "sha256:892fe0d01eb83bbeef6c69cb87b92ed01815f532c90272948d06a60bf545c7da",
      "size_before": 20211,
      "size": 20250
    },
    {
      "page": "三体III-30-第三部·第四章",
      "rev_id": "20260426-192927-ea2f53",
      "timestamp": "2026-04-26T19:29:27+00:00",
      "author": "baojie",
      "summary": "Butler R1-R16：新增16个核心词条，页面总数160",
      "parent_rev": "20260426-191042-9492ab",
      "content_hash": "sha256:ea2f538e6043e78fc484cd582d0890551f97417e8dfdb1cca02a09752df356cb",
      "size_before": 47995,
      "size": 48047
    },
    {
      "page": "三体III-31-第三部·第五章",
      "rev_id": "20260426-192927-86785b",
      "timestamp": "2026-04-26T19:29:27+00:00",
      "author": "baojie",
      "summary": "Butler R1-R16：新增16个核心词条，页面总数160",
      "parent_rev": "20260426-191042-77824a",
      "content_hash": "sha256:86785b9f9f18c00c20bc9cf57b895e3c4536443fb42b10933e3d42cb23316064",
      "size_before": 39868,
      "size": 39876
    },
    {
      "page": "三体III-33-第三部·第七章",
      "rev_id": "20260426-192927-58c013",
      "timestamp": "2026-04-26T19:29:27+00:00",
      "author": "baojie",
      "summary": "Butler R1-R16：新增16个核心词条，页面总数160",
      "parent_rev": "20260426-191042-4b3de9",
      "content_hash": "sha256:58c013faba8fbd4655912793e10ac63d8b243086908f0ae94ef82236bc44d9ac",
      "size_before": 25367,
      "size": 25415
    },
    {
      "page": "三体III-34-第三部·第八章",
      "rev_id": "20260426-192927-b3830b",
      "timestamp": "2026-04-26T19:29:27+00:00",
      "author": "baojie",
      "summary": "Butler R1-R16：新增16个核心词条，页面总数160",
      "parent_rev": "20260426-191042-5c6ec5",
      "content_hash": "sha256:b3830b36e184e4ba77aa2b4670fdee8a072768d5a6401b638dca8731b88c96af",
      "size_before": 17088,
      "size": 17119
    },
    {
      "page": "三体III-35-第三部·第九章",
      "rev_id": "20260426-192927-53374e",
      "timestamp": "2026-04-26T19:29:27+00:00",
      "author": "baojie",
      "summary": "Butler R1-R16：新增16个核心词条，页面总数160",
      "parent_rev": "20260426-191042-bc4c0f",
      "content_hash": "sha256:53374e42374603f9df5f4183022f658da24ed2e7ffa552df0218fd9bde7e271a",
      "size_before": 33577,
      "size": 33585
    },
    {
      "page": "三体III-36-第三部·第十章",
      "rev_id": "20260426-192927-6941ba",
      "timestamp": "2026-04-26T19:29:27+00:00",
      "author": "baojie",
      "summary": "Butler R1-R16：新增16个核心词条，页面总数160",
      "parent_rev": "20260426-191042-f02a9c",
      "content_hash": "sha256:6941ba22a59e832447cce017e5550272846c27823ce54609b01b67ec7c709812",
      "size_before": 35253,
      "size": 35284
    },
    {
      "page": "三体III-37-第三部·第十一章",
      "rev_id": "20260426-192927-2f875d",
      "timestamp": "2026-04-26T19:29:27+00:00",
      "author": "baojie",
      "summary": "Butler R1-R16：新增16个核心词条，页面总数160",
      "parent_rev": "20260426-191042-a31724",
      "content_hash": "sha256:2f875d8a46617427b61c3c2d3aa1bb4f8c142cbdaa315bc6e9f062c83a0cd9bc",
      "size_before": 17565,
      "size": 17592
    },
    {
      "page": "三体III-38-第三部·第十二章",
      "rev_id": "20260426-192927-e29c22",
      "timestamp": "2026-04-26T19:29:27+00:00",
      "author": "baojie",
      "summary": "Butler R1-R16：新增16个核心词条，页面总数160",
      "parent_rev": "20260426-191042-fa396d",
      "content_hash": "sha256:e29c229d58e95986f575d4a5df072485db2ddf635b0117294ed6a8b2363ad3f0",
      "size_before": 17495,
      "size": 17499
    },
    {
      "page": "三体III-39-第四部·第一章",
      "rev_id": "20260426-192927-0d4891",
      "timestamp": "2026-04-26T19:29:27+00:00",
      "author": "baojie",
      "summary": "Butler R1-R16：新增16个核心词条，页面总数160",
      "parent_rev": "20260426-191042-447801",
      "content_hash": "sha256:0d4891d060a84c531473352dfe2fd2c196bdc3391c43e5fab42d7fe21e9b55f0",
      "size_before": 41108,
      "size": 41139
    },
    {
      "page": "三体III-40-第四部·第二章",
      "rev_id": "20260426-192927-4b66b2",
      "timestamp": "2026-04-26T19:29:27+00:00",
      "author": "baojie",
      "summary": "Butler R1-R16：新增16个核心词条，页面总数160",
      "parent_rev": "20260426-191042-384047",
      "content_hash": "sha256:4b66b258639743cbe15609d29b898d9fe115592e18571308ca7bf3917a4e3fab",
      "size_before": 14928,
      "size": 14932
    },
    {
      "page": "三体III-41-第四部·第三章",
      "rev_id": "20260426-192927-99993b",
      "timestamp": "2026-04-26T19:29:27+00:00",
      "author": "baojie",
      "summary": "Butler R1-R16：新增16个核心词条，页面总数160",
      "parent_rev": "20260426-191042-7fd261",
      "content_hash": "sha256:99993b0ba47821c6abf84f854099b82f7a86906cd849cf21a2b72ff3fae00d10",
      "size_before": 36214,
      "size": 36245
    },
    {
      "page": "三体III-42-第五部·第一章",
      "rev_id": "20260426-192927-3f699d",
      "timestamp": "2026-04-26T19:29:27+00:00",
      "author": "baojie",
      "summary": "Butler R1-R16：新增16个核心词条，页面总数160",
      "parent_rev": "20260426-191042-a0a0ad",
      "content_hash": "sha256:3f699d4378e4e28c203cf47fa01a21aa30ad377629c83eab9982b622fc08a9fe",
      "size_before": 14800,
      "size": 14827
    },
    {
      "page": "三体III-43-第五部·第二章",
      "rev_id": "20260426-192927-be733e",
      "timestamp": "2026-04-26T19:29:27+00:00",
      "author": "baojie",
      "summary": "Butler R1-R16：新增16个核心词条，页面总数160",
      "parent_rev": "20260426-191042-86036d",
      "content_hash": "sha256:be733e8b899a88dd0c213dc087ae8ca49df0af1d4a78aa576faa736f4a9a53b0",
      "size_before": 7244,
      "size": 7271
    },
    {
      "page": "三体III-44-第五部·第三章",
      "rev_id": "20260426-192927-4ff732",
      "timestamp": "2026-04-26T19:29:27+00:00",
      "author": "baojie",
      "summary": "Butler R1-R16：新增16个核心词条，页面总数160",
      "parent_rev": "20260426-191042-b4c8f3",
      "content_hash": "sha256:4ff7329d4e8b0af0bd0ddd63ca755a6f77f5043fe19c3fbb5b659155cb22adf7",
      "size_before": 41172,
      "size": 41207
    },
    {
      "page": "三体III-45-第五部·第四章",
      "rev_id": "20260426-192927-84101a",
      "timestamp": "2026-04-26T19:29:27+00:00",
      "author": "baojie",
      "summary": "Butler R1-R16：新增16个核心词条，页面总数160",
      "parent_rev": "20260426-191042-d06cc3",
      "content_hash": "sha256:84101a31d1a36c96b899d4bfd694198f359717b6c4b78a1f47e45d1b1badbaf1",
      "size_before": 32675,
      "size": 32706
    },
    {
      "page": "三体III-46-第五部·第五章",
      "rev_id": "20260426-192927-220017",
      "timestamp": "2026-04-26T19:29:27+00:00",
      "author": "baojie",
      "summary": "Butler R1-R16：新增16个核心词条，页面总数160",
      "parent_rev": "20260426-191042-192e57",
      "content_hash": "sha256:22001759e59fac5d2fd36e01cb4e314a7c3c8c58e31058e9ffee34ecd8140948",
      "size_before": 61958,
      "size": 61978
    },
    {
      "page": "三体III-47-第六部·第一章",
      "rev_id": "20260426-192927-796543",
      "timestamp": "2026-04-26T19:29:27+00:00",
      "author": "baojie",
      "summary": "Butler R1-R16：新增16个核心词条，页面总数160",
      "parent_rev": "20260426-191042-69e388",
      "content_hash": "sha256:79654319a1168b20117f3aa8207066cc7ea13f912e7bc6af2417973f77557bc2",
      "size_before": 64536,
      "size": 64567
    },
    {
      "page": "三体III-48-第六部·第二章",
      "rev_id": "20260426-192927-cc197d",
      "timestamp": "2026-04-26T19:29:27+00:00",
      "author": "baojie",
      "summary": "Butler R1-R16：新增16个核心词条，页面总数160",
      "parent_rev": "20260426-191042-bcb049",
      "content_hash": "sha256:cc197d7e181dc80342651eb1ed3a7832e761cb557d25d261b28a5450216188ff",
      "size_before": 20074,
      "size": 20078
    },
    {
      "page": "三体III-49-第六部·第三章",
      "rev_id": "20260426-192927-ca2232",
      "timestamp": "2026-04-26T19:29:27+00:00",
      "author": "baojie",
      "summary": "Butler R1-R16：新增16个核心词条，页面总数160",
      "parent_rev": "20260426-191042-174a91",
      "content_hash": "sha256:ca223296ac75e17e0c453675b33c279da9a5f5ab8256010e5256a0de4e3d6e81",
      "size_before": 29368,
      "size": 29380
    },
    {
      "page": "三体III-50-第六部·第四章",
      "rev_id": "20260426-192927-1b9bc6",
      "timestamp": "2026-04-26T19:29:27+00:00",
      "author": "baojie",
      "summary": "Butler R1-R16：新增16个核心词条，页面总数160",
      "parent_rev": "20260426-191042-bc7d83",
      "content_hash": "sha256:1b9bc6a2cecad2e1234ff5a03af3ec786cbca2ba5f2c97581b31cde216210f93",
      "size_before": 12336,
      "size": 12367
    },
    {
      "page": "三体文明",
      "rev_id": "20260426-194955-3e97e2",
      "timestamp": "2026-04-26T19:49:55+00:00",
      "author": "baojie",
      "summary": "为23个词条页面写入 quality 等级字段",
      "parent_rev": "20260426-183801-c26886",
      "content_hash": "sha256:3e97e26872cc6047f7ac57c4b7e8a73fc74f33fb81bcbe5765b9d57296c1a1a0",
      "size_before": 2021,
      "size": 2041
    },
    {
      "page": "三体星系",
      "rev_id": "20260426-194955-37855f",
      "timestamp": "2026-04-26T19:49:55+00:00",
      "author": "baojie",
      "summary": "为23个词条页面写入 quality 等级字段",
      "parent_rev": "20260426-192542-0f2483",
      "content_hash": "sha256:37855f6ee006f739063bbbf51707a0ab4effc13bd42c9bbdea826201ca5b9870",
      "size_before": 2204,
      "size": 2236
    },
    {
      "page": "二向箔",
      "rev_id": "20260426-194955-11005b",
      "timestamp": "2026-04-26T19:49:55+00:00",
      "author": "baojie",
      "summary": "为23个词条页面写入 quality 等级字段",
      "parent_rev": "20260426-183801-1c78af",
      "content_hash": "sha256:11005b147d4b298397c6d99d1ca31bd67a037617d02c7d4789ebe5d2769de133",
      "size_before": 1568,
      "size": 1600
    },
    {
      "page": "云天明",
      "rev_id": "20260426-194955-636d48",
      "timestamp": "2026-04-26T19:49:55+00:00",
      "author": "baojie",
      "summary": "为23个词条页面写入 quality 等级字段",
      "parent_rev": "20260426-192542-50fa12",
      "content_hash": "sha256:636d48e2009323c7d6a8776736e7556b9ec28c6d03075739d6767bad43b06b61",
      "size_before": 2356,
      "size": 2376
    },
    {
      "page": "光速飞船",
      "rev_id": "20260426-194955-5079f0",
      "timestamp": "2026-04-26T19:49:55+00:00",
      "author": "baojie",
      "summary": "为23个词条页面写入 quality 等级字段",
      "parent_rev": "20260426-192927-5681fa",
      "content_hash": "sha256:5079f01ba20733fe1a7fa732ce4e240105398668a35a6594fc01b018dc8f4061",
      "size_before": 2788,
      "size": 2808
    },
    {
      "page": "危机纪元",
      "rev_id": "20260426-194955-c269ef",
      "timestamp": "2026-04-26T19:49:55+00:00",
      "author": "baojie",
      "summary": "为23个词条页面写入 quality 等级字段",
      "parent_rev": "20260426-192542-9888a8",
      "content_hash": "sha256:c269eff4771d45acf737c01f9e283cd01f78421c05b5ba57869c7c05ccecdb18",
      "size_before": 2641,
      "size": 2676
    },
    {
      "page": "史强",
      "rev_id": "20260426-194955-733090",
      "timestamp": "2026-04-26T19:49:55+00:00",
      "author": "baojie",
      "summary": "为23个词条页面写入 quality 等级字段",
      "parent_rev": "20260426-192927-080d6d",
      "content_hash": "sha256:7330909155ade8f9989504c740f0b242ffa225017ccf94e8822063acabe716ee",
      "size_before": 2180,
      "size": 2215
    },
    {
      "page": "叶文洁",
      "rev_id": "20260426-194955-e17771",
      "timestamp": "2026-04-26T19:49:55+00:00",
      "author": "baojie",
      "summary": "为23个词条页面写入 quality 等级字段",
      "parent_rev": "20260426-183801-9a1b40",
      "content_hash": "sha256:e17771e435d49c9c9c4047a70c55f8e80384717ae9ab89173832e1d100b9acdf",
      "size_before": 1875,
      "size": 1892
    },
    {
      "page": "地球三体组织",
      "rev_id": "20260426-194955-e84fda",
      "timestamp": "2026-04-26T19:49:55+00:00",
      "author": "baojie",
      "summary": "为23个词条页面写入 quality 等级字段",
      "parent_rev": "20260426-192542-32ff21",
      "content_hash": "sha256:e84fda76255279875ca390424a5357ec08a9ec70bc1398a87c8982820ee85dc3",
      "size_before": 2336,
      "size": 2368
    },
    {
      "page": "太阳系",
      "rev_id": "20260426-194955-c801d5",
      "timestamp": "2026-04-26T19:49:55+00:00",
      "author": "baojie",
      "summary": "为23个词条页面写入 quality 等级字段",
      "parent_rev": "20260426-192927-8850eb",
      "content_hash": "sha256:c801d50909b8277afbf98dd397b1d73602debd16dff90dc49610322faafe67ce",
      "size_before": 2028,
      "size": 2063
    },
    {
      "page": "威慑纪元",
      "rev_id": "20260426-194955-e10427",
      "timestamp": "2026-04-26T19:49:55+00:00",
      "author": "baojie",
      "summary": "为23个词条页面写入 quality 等级字段",
      "parent_rev": "20260426-192542-3a6444",
      "content_hash": "sha256:e10427222b160f26cd44d14c983af4ca6a184231b194cdac93856925ed9f49d8",
      "size_before": 2612,
      "size": 2647
    },
    {
      "page": "宇宙社会学",
      "rev_id": "20260426-194955-bc9d77",
      "timestamp": "2026-04-26T19:49:55+00:00",
      "author": "baojie",
      "summary": "为23个词条页面写入 quality 等级字段",
      "parent_rev": "20260426-192542-3f4ed6",
      "content_hash": "sha256:bc9d7714a5964d379adfd893d2907b79c8f45570ad4c90f627e4f36cc70ac47f",
      "size_before": 2552,
      "size": 2572
    },
    {
      "page": "执剑人",
      "rev_id": "20260426-194955-05cada",
      "timestamp": "2026-04-26T19:49:55+00:00",
      "author": "baojie",
      "summary": "为23个词条页面写入 quality 等级字段",
      "parent_rev": "20260426-192542-1fcc95",
      "content_hash": "sha256:05cadafbc24aaf923480a5a2bef005f3f4298727d1527286880b06716cddc85c",
      "size_before": 3052,
      "size": 3072
    },
    {
      "page": "智子",
      "rev_id": "20260426-194955-468a9a",
      "timestamp": "2026-04-26T19:49:55+00:00",
      "author": "baojie",
      "summary": "为23个词条页面写入 quality 等级字段",
      "parent_rev": "20260426-183801-b7e7c0",
      "content_hash": "sha256:468a9a7281e540d448e5d5e8a9eb4739373abfbbf19400f4112b55ac58d3559f",
      "size_before": 1675,
      "size": 1692
    },
    {
      "page": "水滴探测器",
      "rev_id": "20260426-194955-94e750",
      "timestamp": "2026-04-26T19:49:55+00:00",
      "author": "baojie",
      "summary": "为23个词条页面写入 quality 等级字段",
      "parent_rev": "20260426-192542-449b5f",
      "content_hash": "sha256:94e750d37f864b2d3e4d908dd1abd36a857249fba229a91f867e52b4c2d6c003",
      "size_before": 2704,
      "size": 2721
    },
    {
      "page": "汪淼",
      "rev_id": "20260426-194955-f624e3",
      "timestamp": "2026-04-26T19:49:55+00:00",
      "author": "baojie",
      "summary": "为23个词条页面写入 quality 等级字段",
      "parent_rev": "20260426-192542-959a8f",
      "content_hash": "sha256:f624e326e4998caccd00c2db7756bdf24ef84d387ab5114ad078ffdeeeefc8d9",
      "size_before": 2225,
      "size": 2245
    },
    {
      "page": "程心",
      "rev_id": "20260426-194955-a03ce7",
      "timestamp": "2026-04-26T19:49:55+00:00",
      "author": "baojie",
      "summary": "为23个词条页面写入 quality 等级字段",
      "parent_rev": "20260426-183801-bcef72",
      "content_hash": "sha256:a03ce7fd4defc7cbb9fcc864e516f17552cf9fd51acc0e9e1269f70a304d9dd0",
      "size_before": 1455,
      "size": 1487
    },
    {
      "page": "章北海",
      "rev_id": "20260426-194955-5f209d",
      "timestamp": "2026-04-26T19:49:55+00:00",
      "author": "baojie",
      "summary": "为23个词条页面写入 quality 等级字段",
      "parent_rev": "20260426-192542-daf409",
      "content_hash": "sha256:5f209d920da0ad905218690d8a4fdbd9ddc52f38ab12ad6220b0c0faa0201ff6",
      "size_before": 2410,
      "size": 2430
    },
    {
      "page": "红岸基地",
      "rev_id": "20260426-194955-fca2d0",
      "timestamp": "2026-04-26T19:49:55+00:00",
      "author": "baojie",
      "summary": "为23个词条页面写入 quality 等级字段",
      "parent_rev": "20260426-183801-0a866d",
      "content_hash": "sha256:fca2d0efe6725154624a7d7fee94e9f1dc808e78002f4a52a29fd8f6a26ab12e",
      "size_before": 1271,
      "size": 1303
    },
    {
      "page": "罗辑",
      "rev_id": "20260426-194955-63f490",
      "timestamp": "2026-04-26T19:49:55+00:00",
      "author": "baojie",
      "summary": "为23个词条页面写入 quality 等级字段",
      "parent_rev": "20260426-183801-76fa07",
      "content_hash": "sha256:63f4907b9ba9e88234566074f51c94c0fe5a472f160ba327a28d23dc23eba7e9",
      "size_before": 1976,
      "size": 1996
    },
    {
      "page": "费米悖论",
      "rev_id": "20260426-194955-299f7c",
      "timestamp": "2026-04-26T19:49:55+00:00",
      "author": "baojie",
      "summary": "为23个词条页面写入 quality 等级字段",
      "parent_rev": "20260426-192927-4c2755",
      "content_hash": "sha256:299f7c80eb076fca8069baec182852d7f83d2e69be13f6059eb5a08e269a68fb",
      "size_before": 2083,
      "size": 2115
    },
    {
      "page": "面壁者",
      "rev_id": "20260426-194955-7c9e99",
      "timestamp": "2026-04-26T19:49:55+00:00",
      "author": "baojie",
      "summary": "为23个词条页面写入 quality 等级字段",
      "parent_rev": "20260426-192542-1eab73",
      "content_hash": "sha256:7c9e99662451f6294a82e978279929fc4fbb866dc3f37feb82c353b577c63fc5",
      "size_before": 2855,
      "size": 2875
    },
    {
      "page": "黑暗森林法则",
      "rev_id": "20260426-194955-9cf91b",
      "timestamp": "2026-04-26T19:49:55+00:00",
      "author": "baojie",
      "summary": "为23个词条页面写入 quality 等级字段",
      "parent_rev": "20260426-183801-3efe98",
      "content_hash": "sha256:9cf91be539611f835d0de8cb2833ec8567e71536269f517ce209c38efdeb0794",
      "size_before": 2407,
      "size": 2424
    }
  ],
  "rotations": 0
}
